[
    {
        "id": "3af82246.3634ae",
        "type": "tab",
        "label": "Flow 1",
        "disabled": false,
        "info": ""
    },
    {
        "id": "9d93e5cf.bfcaf8",
        "type": "inject",
        "z": "3af82246.3634ae",
        "name": "",
        "props": [
            {
                "p": "payload"
            },
            {
                "p": "topic",
                "vt": "str"
            }
        ],
        "repeat": "",
        "crontab": "",
        "once": false,
        "onceDelay": 0.1,
        "topic": "",
        "payload": "",
        "payloadType": "date",
        "x": 230,
        "y": 180,
        "wires": [
            [
                "62521659.9b89e8"
            ]
        ]
    },
    {
        "id": "62521659.9b89e8",
        "type": "debug",
        "z": "3af82246.3634ae",
        "name": "",
        "active": true,
        "tosidebar": true,
        "console": false,
        "tostatus": false,
        "complete": "false",
        "statusVal": "",
        "statusType": "auto",
        "x": 430,
        "y": 220,
        "wires": []
    }
]